MANIFEST.in
README.rst
setup.py
redisEventTracker/__init__.py
redisEventTracker/tests/__init__.py
redisEventTracker/tests/tests.py
redis_event_tracker.egg-info/PKG-INFO
redis_event_tracker.egg-info/SOURCES.txt
redis_event_tracker.egg-info/dependency_links.txt
redis_event_tracker.egg-info/top_level.txt