Metadata-Version: 1.1
Name: redis-event-tracker
Version: 0.0.9
Summary: Track your events in redis
Home-page: https://github.com/Keyintegrity/redisEventTracker
Author: Aleksey Pivovarov
Author-email: lexapi@gmail.com
License: MIT License
Download-URL: https://github.com/Keyintegrity/redisEventTracker/archive/master.zip
Keywords: redis events track
Platform: UNKNOWN
Classifier: Development Status :: 4 - Beta
Classifier: Environment :: Console
Classifier: Environment :: Web Environment
Classifier: Operating System :: OS Independent
Classifier: Intended Audience :: Developers
Classifier: Intended Audience :: System Administrators
Classifier: Programming Language :: Python :: 2.7
Classifier: Topic :: Software Development :: Libraries :: Application Frameworks
Classifier: Topic :: Software Development :: Libraries :: Python Modules
Requires: redis (>= 2.7.6)
